optuml/__init__.py
optuml/optuml.py
tests/__init__.py
tests/test_optimizer.py
optuml-0.2.3.dist-info/LICENSE
optuml-0.2.3.dist-info/METADATA
optuml-0.2.3.dist-info/WHEEL
optuml-0.2.3.dist-info/top_level.txt
optuml-0.2.3.dist-info/RECORD
