Metadata-Version: 2.1
Name: optuml
Version: 0.2.3
Summary: Hyperparameter optimization for multiple machine learning algorithms using Optuna, with Scikit-learn API
Home-page: https://github.com/filipsPL/optuml
Author: Filip S.
Author-email: filip.ursynow@gmail.com
Classifier: Programming Language :: Python :: 3
Classifier: License :: OSI Approved :: MIT License
Classifier: Operating System :: OS Independent
Requires-Python: >=3.8
License-File: LICENSE
Requires-Dist: optuna>=3.0.1
Requires-Dist: scikit-learn
Requires-Dist: catboost
Requires-Dist: graphviz
Requires-Dist: xgboost
Requires-Dist: numpy
Requires-Dist: wrapt-timeout-decorator
